{
    "stream": {
        "sticked": false,
        "index": 0,
        "tab": 0
    },
    "contacts": {
        "index": 2,
        "tab": 1
    },
    "policies": {
        "index": 1,
        "tab": 2,
        "noMaxHeight": true
    },
    "renewals": {
        "index": 3,
        "tab": 2,
        "noMaxHeight": true
    },
    "activityLogs": {
        "index": 4,
        "tab": 3
    },
    "emails": {
        "index": 5,
        "tab": 3
    },
    "meetings": {
        "index": 6,
        "tab": 3
    },
    "calls": {
        "index": 7,
        "tab": 3
    },
    "tasks": {
        "index": 8,
        "tab": 3
    },
    "opportunities": {
        "index": 9,
        "tab": 4
    },
    "cases": {
        "index": 10,
        "tab": 6
    },
    "commissions": {
        "index": 11,
        "tab": 6
    },
    "activities": {
        "disabled": true
    },
    "history": {
        "disabled": true
    },
    "_delimiter_": {
        "disabled": true
    }
}
