[
    {
        "rows": [
            [
                {
                    "name": "accountStatus"
                },
                {
                    "name": "scoreTier"
                }
            ],
            [
                {
                    "name": "totalActivePremium"
                },
                {
                    "name": "activePolicyCount"
                }
            ],
            [
                {
                    "name": "nextXDate"
                },
                {
                    "name": "nextXDateLob"
                }
            ],
            [
                {
                    "name": "retentionRisk"
                },
                {
                    "name": "rateIncreaseFlag"
                }
            ]
        ],
        "style": "default",
        "name": "relationshipOverview",
        "label": "Relationship Overview"
    },
    {
        "rows": [
            [
                {
                    "name": "name"
                },
                {
                    "name": "accountType"
                }
            ],
            [
                {
                    "name": "assignedUser"
                },
                {
                    "name": "clientSince"
                }
            ],
            [
                {
                    "name": "phoneNumber"
                },
                {
                    "name": "emailAddress"
                }
            ],
            [
                {
                    "name": "billingAddress"
                },
                {
                    "name": "mailingAddress"
                }
            ]
        ],
        "style": "default",
        "name": "accountInfo",
        "label": "Client Snapshot"
    },
    {
        "rows": [],
        "style": "default",
        "tabBreak": true,
        "tabLabel": "Contacts",
        "name": "contactsAnchor",
        "label": "Contacts"
    },
    {
        "rows": [],
        "style": "default",
        "tabBreak": true,
        "tabLabel": "Policies",
        "name": "policiesAnchor",
        "label": "Policies"
    },
    {
        "rows": [],
        "style": "default",
        "tabBreak": true,
        "tabLabel": "Activity",
        "name": "activityAnchor",
        "label": "Activity"
    },
    {
        "rows": [
            [
                {
                    "name": "intelLegalName"
                },
                {
                    "name": "intelDba"
                }
            ],
            [
                {
                    "name": "businessEntity"
                },
                {
                    "name": "cYearBusinessEst"
                }
            ],
            [
                {
                    "name": "yearsInBusiness"
                },
                {
                    "name": "fein"
                }
            ],
            [
                {
                    "name": "industry"
                },
                {
                    "name": "sicCode"
                }
            ],
            [
                {
                    "name": "numberOfEmployees"
                },
                {
                    "name": "websiteUrl"
                }
            ],
            [
                {
                    "name": "linkedinUrl"
                },
                {
                    "name": "googleDriveFolderUrl"
                }
            ]
        ],
        "style": "default",
        "tabBreak": true,
        "tabLabel": "Profile",
        "name": "profileIdentity",
        "customLabel": "Business Identity"
    },
    {
        "rows": [
            [
                {
                    "name": "aiAssessment"
                }
            ],
            [
                {
                    "name": "communicationNotes"
                }
            ],
            [
                {
                    "name": "referralSource"
                },
                {
                    "name": "referralName"
                }
            ],
            [
                {
                    "name": "preferredContact"
                },
                {
                    "name": "bestTimeToCall"
                }
            ],
            [
                {
                    "name": "lastContactDate"
                },
                {
                    "name": "lastContactType"
                }
            ],
            [
                {
                    "name": "lastContactOutcome"
                },
                {
                    "name": "lastContactBy"
                }
            ]
        ],
        "style": "default",
        "name": "relationshipSummary",
        "customLabel": "Relationship Summary"
    },
    {
        "rows": [
            [
                {
                    "name": "intelBbbRating"
                },
                {
                    "name": "intelBbbAccredited"
                }
            ],
            [
                {
                    "name": "intelBbbComplaints"
                },
                {
                    "name": "intelGrowthIndicator"
                }
            ],
            [
                {
                    "name": "claimsCount3yr"
                },
                {
                    "name": "claimsOpen"
                }
            ],
            [
                {
                    "name": "lastClaimDate"
                },
                {
                    "name": "lastClaimType"
                }
            ],
            [
                {
                    "name": "claimsNotes"
                }
            ]
        ],
        "style": "default",
        "name": "reputationAndRisk",
        "customLabel": "Reputation & Risk"
    },
    {
        "rows": [
            [
                {
                    "name": "communicationNotes"
                }
            ],
            [
                {
                    "name": "lastContactDate"
                },
                {
                    "name": "lastContactType"
                }
            ],
            [
                {
                    "name": "referralSource"
                },
                {
                    "name": "referralName"
                }
            ],
            [
                {
                    "name": "googleDriveFolderUrl"
                },
                {
                    "name": "retentionRisk"
                }
            ]
        ],
        "dynamicLogicVisible": {
            "conditionGroup": [
                {
                    "type": "equals",
                    "attribute": "accountType",
                    "value": "Group Benefits"
                }
            ]
        },
        "style": "default",
        "tabBreak": true,
        "tabLabel": "Relationship",
        "name": "gbRelationship",
        "customLabel": "Relationship Notes"
    },
    {
        "rows": [
            [
                {
                    "name": "intelPackRun"
                },
                {
                    "name": "intelPackLastRun"
                }
            ],
            [
                {
                    "name": "momentumClientId"
                },
                {
                    "name": "momentumLastSynced"
                }
            ],
            [
                {
                    "name": "intelSources"
                },
                {
                    "name": "intelSourcesHit"
                }
            ]
        ],
        "style": "default",
        "tabBreak": true,
        "tabLabel": "Internal",
        "name": "internalSystems",
        "label": "Internal Systems"
    }
]
